source/ram/sdp_1clk_bram.v
module sdp_1clk_bram #(
    parameter ADDR_WIDTH=8,
    parameter DATA_WIDTH=12
)(
    input  wire                  clk,
    input  wire [ADDR_WIDTH-1:0] rd_addr,
    input  wire [ADDR_WIDTH-1:0] wr_addr,
    input  wire                  wr_en,
    input  wire [DATA_WIDTH-1:0] wr_data,
    output reg  [DATA_WIDTH-1:0] rd_data
);
    localparam RAM_DEPTH = 2**ADDR_WIDTH;
    (* ram_style = "block" *)  reg [DATA_WIDTH-1:0] ram [RAM_DEPTH-1:0];

    // ** UNCOMMENT FOR DEBUGGING BRAM CONTENTS ** //
    // generate
    // genvar idx;
    // for(idx = 0; idx < RAM_DEPTH; idx = idx+1) begin: ram_dump
    //     wire [DATA_WIDTH-1:0] tmp;
    //     assign tmp = ram[idx];
    // end
    // endgenerate

    always@(posedge clk) begin
        rd_data <= ram[rd_addr];
        if (wr_en) ram[wr_addr] <= wr_data;
    end

endmodule

source/fifo/sync_fifo.v
module sync_fifo #(
    parameter ADDR_WIDTH = 3,
    parameter DATA_WIDTH = 24
)(
    input  wire clk,
    input  wire rst,
    input  wire wr_en,
    input  wire rd_en,
    input  wire [DATA_WIDTH-1:0] wr_data,
    output wire [DATA_WIDTH-1:0] rd_data,
    output wire  empty,
    output wire  full,
    input  wire  jump,
    input  wire [ADDR_WIDTH-1:0] jump_value,
    output wire  jump_error
);

    reg                   rd_wrap = 0;
    reg                   wr_wrap = 0;
    reg  [ADDR_WIDTH-1:0] rd_ptr  = 0;
    reg  [ADDR_WIDTH-1:0] wr_ptr  = 0;

    reg                   wr_wrap_reg = 0;
    reg  [ADDR_WIDTH-1:0] wr_ptr_reg  = 0;

    reg wr_en_reg = 0;

    wire                   jump_wrap;
    wire  [ADDR_WIDTH-1:0] jump_ptr;

    assign empty = (rd_wrap == wr_wrap_reg) && (rd_ptr == wr_ptr_reg); // wraps equal, ptrs equal
    assign full  = (rd_wrap != wr_wrap_reg) && (rd_ptr == wr_ptr_reg); // wraps not equal, ptrs equal

    assign {jump_wrap, jump_ptr} = {rd_wrap, rd_ptr} + {1'b0,jump_value};
    assign jump_error = (jump_wrap == wr_wrap_reg) && (jump_ptr >= wr_ptr_reg);


    always@(posedge clk) begin
        if (rst) begin
            {rd_wrap, rd_ptr} <= 0;
            {wr_wrap, wr_ptr} <= 0;
            {wr_wrap_reg, wr_ptr_reg} <= 0;
        end else begin
            if (jump && !jump_error) begin
                {rd_wrap, rd_ptr} <= {jump_wrap, jump_ptr};
            end else begin
                {rd_wrap, rd_ptr} <= {rd_wrap, rd_ptr} + (rd_en && !empty);
            end
            {wr_wrap, wr_ptr} <= {wr_wrap, wr_ptr} + (wr_en && !full);
            {wr_wrap_reg, wr_ptr_reg} <= {wr_wrap, wr_ptr};
        end
    end

    sdp_1clk_bram #(
        .ADDR_WIDTH(ADDR_WIDTH),
        .DATA_WIDTH(DATA_WIDTH)
    ) sdp_1clk_bram_u1 (
        .clk    (clk),
        .rd_addr(rd_ptr),
        .wr_addr(wr_ptr),
        .wr_en  (wr_en && !full),
        .wr_data(wr_data),
        .rd_data(rd_data)
    );

endmodule

source/detect_preamble/preamble_correlator.v
module preamble_correlator #(
    parameter       LENGTH = 64,
    parameter       BANKS  = 16
)(
    input  wire                         clk,
    input  wire                         rst,
    input  wire                         in_dat, 
    input  wire                         in_vld,
    output reg  [CORR_WIDTH*BANKS-1:0]  corr_dat,
    output reg                          corr_vld,
    output wire                         all_zeros
);
    localparam CORR_WIDTH = $clog2(LENGTH+1);

    reg [LENGTH-1:0] shift_register = 0;
    reg [LENGTH-1:0]        correlator_coeffs [BANKS-1:0];
    reg [CORR_WIDTH-1:0]    correlator_lengths [BANKS-1:0];

    initial begin
        $readmemb("../source/detect_preamble/correlator_coeffs.txt", correlator_coeffs);
        $readmemb("../source/detect_preamble/correlator_lengths.txt", correlator_lengths);
    end

    always @(posedge clk) begin
        if (rst) begin
            shift_register <= 0;
            corr_vld <= 0;
        end else begin
            if (in_vld) begin
                shift_register <= {shift_register[LENGTH-2:0], in_dat};
            end
            corr_vld <= in_vld;
        end
    end

    always@(*) begin
        integer i, j;
        for (i=0; i<BANKS; i=i+1) begin
            corr_dat[i*CORR_WIDTH+:CORR_WIDTH] = 0;
            for (j=0; j<LENGTH; j=j+1)
                if (shift_register[j] == correlator_coeffs[i][j] && j < correlator_lengths[i])
                    corr_dat[i*CORR_WIDTH+:CORR_WIDTH]=corr_dat[i*CORR_WIDTH+:CORR_WIDTH]+1;
        end
    end

    assign all_zeros =  ~| shift_register[(LENGTH/2):0];

endmodule

source/detect_preamble/preamble_detector.v
module preamble_detector #(
    parameter       LENGTH = 4,
    parameter       BANKS  = 4,
    parameter       HI_THRESHOLD = 3,
    parameter       LO_THRESHOLD = 2
)(
    input  wire clk,
    input  wire rst,
    input  wire in_dat, 
    input  wire in_vld,
    output wire out_dat,
    output reg  out_vld, // reg
    output wire [BANK_WIDTH-1:0] frequency_bank,
    output wire preamble_detected,
    output wire postamble_detected
);

    localparam BANK_WIDTH = $clog2(BANKS);
    localparam CORR_WIDTH = $clog2(LENGTH+1);
    localparam COUNT_WIDTH = 12;

    localparam IDLE_STATE = 2'd0; // Idling for preamble
    localparam FIND_STATE = 2'd1; // Finding max correlation
    localparam DATA_STATE = 2'd2; // Outputting data

    reg [1:0]              state = IDLE_STATE; //reg
    reg [1:0]              next_state; // combinational, not a register
    reg [COUNT_WIDTH-1:0]  count = 0; // reg
    reg [COUNT_WIDTH-1:0]  next_count; // combinational, not a register

    reg [COUNT_WIDTH-1:0]  offset  = 0; // reg

    reg [BANK_WIDTH-1:0]   cur_bank; // combinational, not a register
    reg [CORR_WIDTH-1:0]   cur_corr; // combinational, not a register

    reg [BANK_WIDTH-1:0]   max_bank; // reg
    reg [CORR_WIDTH-1:0]   max_corr = 0; // reg

    wire [BANKS*CORR_WIDTH-1:0]  corr_dat;
    wire                         corr_vld;

    integer i;

    wire above_thresh;
    wire below_thresh;
    assign above_thresh = (cur_corr >= HI_THRESHOLD);
    assign below_thresh = (cur_corr <= LO_THRESHOLD);

    wire all_zeros;

    wire push;
    wire pop;
    wire fifo_empty;
    wire fifo_full;

    wire fifo_rst;
    wire fifo_jump;
    wire fifo_jump_error;

    assign preamble_detected = (state == FIND_STATE) && (next_state == DATA_STATE);
    assign postamble_detected = (state == DATA_STATE) && (next_state == IDLE_STATE);
    assign frequency_bank = max_bank;

    preamble_correlator #(
        .LENGTH(LENGTH),
        .BANKS (BANKS)
    ) preamble_correlator_u1 (
        .clk (clk),
        .rst (rst),
        .in_dat (in_dat), 
        .in_vld (in_vld),
        .corr_dat(corr_dat),
        .corr_vld(corr_vld),
        .all_zeros(all_zeros)
    );

    // cur_bank and cur_corr determined (combinational) by taking maximum correlator bank
    always@(*) begin
        cur_bank = 0;
        cur_corr = 0;
        for (i=0; i<BANKS; i=i+1) begin
            if (corr_dat[i*CORR_WIDTH+:CORR_WIDTH] > cur_corr) begin
                cur_bank = i;
                cur_corr = corr_dat[i*CORR_WIDTH+:CORR_WIDTH];
            end
        end
    end

    // max_bank and max_corr updated (sequential) if in FIND_STATE and new valid sample
    always@(posedge clk) begin
        if (rst) begin
            max_corr <= 0;
            max_bank <= 0;
            offset   <= 0;
        end else begin
            if ((state == FIND_STATE || next_state == FIND_STATE) && in_vld && cur_corr > max_corr) begin
                max_corr <= cur_corr;
                max_bank <= cur_bank;
                offset   <= count;
            end else if (state == DATA_STATE) begin
                max_corr <= 0;
                max_bank <= 0;
                offset   <= 0;
            end
        end
    end

    sync_fifo #(
        .ADDR_WIDTH(COUNT_WIDTH),
        .DATA_WIDTH(1)
    ) sync_fifo_u1 (
        .clk(clk),
        .rst(fifo_rst),
        .wr_en(push),
        .rd_en(pop),
        .wr_data(in_dat),
        .rd_data(out_dat),
        .empty(fifo_empty),
        .full(fifo_full),
        .jump (fifo_jump),
        .jump_value (offset),
        .jump_error (fifo_jump_error)
    );

    assign push = in_vld && (state != IDLE_STATE || next_state != IDLE_STATE) && !fifo_full;
    assign pop  = (state == DATA_STATE) && !fifo_empty;

    assign fifo_jump = (state == FIND_STATE && next_state == DATA_STATE);
    assign fifo_rst = (state == IDLE_STATE && next_state == IDLE_STATE); // needs at least 3 cycles of idle state

    // always @(*) if (fifo_jump && fifo_jump_error) $error();

    always@(*) begin
        case(state)
            IDLE_STATE: begin
                next_state = (above_thresh) ? FIND_STATE : IDLE_STATE;
                next_count = 0;
            end
            FIND_STATE: begin
                next_state = (below_thresh) ? DATA_STATE : FIND_STATE;
                next_count = count+push;
            end
            DATA_STATE: begin
                next_state = (all_zeros)    ? IDLE_STATE : DATA_STATE;
                next_count = 0; 
            end
        endcase
    end
    
    always@(posedge clk) begin
        if (rst) begin
            state <= IDLE_STATE;
            count <= 0;
            out_vld <= 0;
        end else begin
            state <= next_state;
            count <= next_count;
            out_vld <= pop;
        end
    end

endmodule

tests/preamble_detector_tb.v
`timescale 1ns/1ps

module preamble_detector_tb;

    parameter LENGTH         = 10;
    parameter BANKS          = 4;
    parameter HI_THRESHOLD   = 10;
    parameter LO_THRESHOLD   = 6;

    parameter NUM_JUNK = 20;
    parameter NUM_DATA = 20;

    localparam BANK_WIDTH = $clog2(BANKS);

    //outputs
    reg out_dat;
    reg out_vld;
    reg [BANK_WIDTH-1:0] frequency_bank;
    reg preamble_detected;
    reg postamble_detected;

    //inputs
    reg  in_dat = 0;
    reg  in_vld = 0;
    reg  clk;

    // generated signals
    reg        queue [$]; 
    reg        rand_data;
    reg [LENGTH-1:0] preamble = 10'b0001100011;//38'b11111111000111000000111000000000111111;
    integer    send_count = 0;
    integer    recv_count = 0;
    reg [1:0]  send_state = 0;
    reg [1:0]  next_state = 0;
    localparam SEND_JUNK = 2'd0, SEND_PREA = 2'd1, SEND_DATA = 2'd2, SEND_ZERO = 2'd3;

    // instantiate top dut
    preamble_detector #(
        .LENGTH       (LENGTH),
        .BANKS        (BANKS),
        .HI_THRESHOLD (HI_THRESHOLD),
        .LO_THRESHOLD (LO_THRESHOLD)
    ) preamble_detector_u1 (
        .clk    (clk),
        .rst    (1'b0),
        .in_dat (in_dat), 
        .in_vld (in_vld),
        .out_dat(out_dat),
        .out_vld(out_vld),
        .frequency_bank     (frequency_bank),
        .preamble_detected  (preamble_detected),
        .postamble_detected (postamble_detected)
    );

    always@(posedge clk) begin
        //if ($urandom_range(1, 0)) begin
        if (1'b0) begin
            in_dat <= $random();
            in_vld <= 1'b0;
        end else begin
            rand_data = $random();
            in_vld <= 1'b1;
            send_state <= next_state;
            send_count <= (next_state != send_state) ? 0 : send_count + 1;
            case(next_state)
                SEND_JUNK: begin
                    in_dat <= rand_data;
                end
                SEND_PREA: begin
                    in_dat <= preamble[LENGTH-1];
                    preamble <= {preamble[LENGTH-2:0], preamble[LENGTH-1]};
                end
                SEND_DATA: begin
                    in_dat <= rand_data;
                    queue.push_back(rand_data);
                end
                SEND_ZERO: begin
                    in_dat <= 1'b0;
                end
            endcase
        end
    end

    always@(posedge clk) begin
        if (send_state == SEND_JUNK) begin
            recv_count <= 0;
        end else if (out_vld && recv_count < NUM_DATA && queue.size()>0) begin
            recv_count <= recv_count+1;
            if (out_dat == queue.pop_front()) begin
                $display ("Correct data: %b, Queue size: %0d, Sim time: %0d", out_dat, queue.size(), $time());
            end else begin
                $display ("Incorrect data: %b, Queue size: %0d, Sim time: %0d", out_dat, queue.size(), $time());
            end
        end
    end

    always @(*) begin
       case(send_state)
            SEND_JUNK: next_state = (send_count == NUM_JUNK-1) ? SEND_PREA : SEND_JUNK;
            SEND_PREA: next_state = (send_count == LENGTH-1) ? SEND_DATA : SEND_PREA;
            SEND_DATA: next_state = (send_count == NUM_DATA-1) ? SEND_ZERO : SEND_DATA;
            SEND_ZERO: next_state = (send_count == 20-1) ? SEND_JUNK : SEND_ZERO;
        endcase
    end

    initial begin
        $dumpfile("dump.vcd");
        $dumpvars;
        clk = 0;
        repeat(900) #5 clk = ~clk;
        $finish;
    end

endmodule

build/dump.vcd
$date
	Sat Mar 29 23:31:21 2025
$end
$version
	Icarus Verilog
$end
$timescale
	1ps
$end
$scope module preamble_detector_tb $end
$var wire 1 ! preamble_detected $end
$var wire 1 " postamble_detected $end
$var wire 1 # out_vld $end
$var wire 1 $ out_dat $end
$var wire 2 % frequency_bank [1:0] $end
$var reg 1 & clk $end
$var reg 1 ' in_dat $end
$var reg 1 ( in_vld $end
$var reg 2 ) next_state [1:0] $end
$var reg 10 * preamble [9:0] $end
$var reg 1 + rand_data $end
$var reg 2 , send_state [1:0] $end
$var integer 32 - recv_count [31:0] $end
$var integer 32 . send_count [31:0] $end
$scope module preamble_detector_u1 $end
$var wire 1 & clk $end
$var wire 1 / fifo_jump $end
$var wire 1 0 fifo_rst $end
$var wire 2 1 frequency_bank [1:0] $end
$var wire 1 ' in_dat $end
$var wire 1 ( in_vld $end
$var wire 1 2 pop $end
$var wire 1 " postamble_detected $end
$var wire 1 ! preamble_detected $end
$var wire 1 3 push $end
$var wire 1 4 rst $end
$var wire 1 $ out_dat $end
$var wire 1 5 fifo_jump_error $end
$var wire 1 6 fifo_full $end
$var wire 1 7 fifo_empty $end
$var wire 1 8 corr_vld $end
$var wire 16 9 corr_dat [15:0] $end
$var wire 1 : below_thresh $end
$var wire 1 ; all_zeros $end
$var wire 1 < above_thresh $end
$var reg 12 = count [11:0] $end
$var reg 2 > cur_bank [1:0] $end
$var reg 4 ? cur_corr [3:0] $end
$var reg 2 @ max_bank [1:0] $end
$var reg 4 A max_corr [3:0] $end
$var reg 12 B next_count [11:0] $end
$var reg 2 C next_state [1:0] $end
$var reg 12 D offset [11:0] $end
$var reg 1 # out_vld $end
$var reg 2 E state [1:0] $end
$var integer 32 F i [31:0] $end
$scope module preamble_correlator_u1 $end
$var wire 1 & clk $end
$var wire 1 ' in_dat $end
$var wire 1 ( in_vld $end
$var wire 1 4 rst $end
$var wire 1 ; all_zeros $end
$var reg 16 G corr_dat [15:0] $end
$var reg 1 8 corr_vld $end
$var reg 10 H shift_register [9:0] $end
$scope begin $unm_blk_75 $end
$var integer 32 I i [31:0] $end
$var integer 32 J j [31:0] $end
$upscope $end
$upscope $end
$scope module sync_fifo_u1 $end
$var wire 1 & clk $end
$var wire 1 7 empty $end
$var wire 1 6 full $end
$var wire 1 / jump $end
$var wire 1 5 jump_error $end
$var wire 12 K jump_value [11:0] $end
$var wire 1 2 rd_en $end
$var wire 1 0 rst $end
$var wire 1 ' wr_data $end
$var wire 1 3 wr_en $end
$var wire 1 $ rd_data $end
$var wire 1 L jump_wrap $end
$var wire 12 M jump_ptr [11:0] $end
$var reg 12 N rd_ptr [11:0] $end
$var reg 1 O rd_wrap $end
$var reg 1 P wr_en_reg $end
$var reg 12 Q wr_ptr [11:0] $end
$var reg 12 R wr_ptr_reg [11:0] $end
$var reg 1 S wr_wrap $end
$var reg 1 T wr_wrap_reg $end
$scope module sdp_1clk_bram_u1 $end
$var wire 1 & clk $end
$var wire 12 U rd_addr [11:0] $end
$var wire 12 V wr_addr [11:0] $end
$var wire 1 ' wr_data $end
$var wire 1 W wr_en $end
$var reg 1 $ rd_data $end
$upscope $end
$upscope $end
$upscope $end
$upscope $end
$enddefinitions $end
#0
$dumpvars
0W
b0 V
b0 U
0T
0S
b0 R
b0 Q
0P
0O
b0 N
b0 M
0L
b0 K
b1010 J
b100 I
b0 H
b101010101010110 G
b100 F
b0 E
b0 D
b0 C
b0 B
b0 A
bx @
b110 ?
b0 >
b0 =
0<
1;
1:
b101010101010110 9
x8
17
06
15
04
03
02
bx 1
10
0/
b0 .
b0 -
b0 ,
x+
b1100011 *
b0 )
0(
0'
0&
bx %
x$
x#
0"
0!
$end
#5000
08
0#
b1 .
1(
0+
1&
#10000
0&
#15000
1'
b10 .
18
1+
1&
#20000
0&
#25000
0:
b100 F
b111 ?
b1010 J
b110011001100111 9
b110011001100111 G
b100 I
0;
b1 H
b11 .
1&
#30000
0&
#35000
b100 F
0:
b1000 ?
b1010 J
b111011101111000 9
b111011101111000 G
b100 I
b100 .
b11 H
1&
#40000
0&
#45000
b10 >
b100 F
0:
b1000 ?
b1010 J
b1000100001100111 9
b1000100001100111 G
b100 I
b111 H
b101 .
1&
#50000
0&
#55000
b100 F
0:
b111 ?
b10 >
b1010 J
b111011101010110 9
b111011101010110 G
b100 I
b110 .
b1111 H
1&
#60000
0&
#65000
b100 F
1:
b110 ?
b10 >
b1010 J
b110011001000101 9
b110011001000101 G
b100 I
b11111 H
b111 .
1&
#70000
0&
#75000
b100 F
b110 ?
b0 >
b1010 J
b101010101010110 9
b101010101010110 G
b100 I
0'
b1000 .
b111111 H
0+
1&
#80000
0&
#85000
b100 F
b110 ?
b1010 J
b101010101010110 9
b101010101010110 G
b100 I
b1111110 H
1'
b1001 .
1+
1&
#90000
0&
#95000
b1 >
b100 F
b110 ?
b1010 J
b100011001100101 9
b100011001100101 G
b100 I
b1010 .
b11111101 H
1&
#100000
0&
#105000
0:
b100 F
b111 ?
b1 >
b1010 J
b11010101110110 9
b11010101110110 G
b100 I
b111111011 H
0'
b1011 .
0+
1&
#110000
0&
#115000
b100 F
1:
b101 ?
b1 >
b1010 J
b101010101010100 9
b101010101010100 G
b100 I
1'
b1100 .
b1111110110 H
1+
1&
#120000
0&
#125000
b100 F
b101 ?
b1 >
b1010 J
b101010101010100 9
b101010101010100 G
b100 I
b1111101101 H
b1101 .
1&
#130000
0&
#135000
b100 F
b101 ?
b1 >
b1010 J
b101010101010100 9
b101010101010100 G
b100 I
0'
b1110 .
b1111011011 H
0+
1&
#140000
0&
#145000
b100 F
b100 ?
b1 >
b1010 J
b100010001000011 9
b100010001000011 G
b100 I
b1110110110 H
1'
b1111 .
1+
1&
#150000
0&
#155000
b100 F
b110 ?
b11 >
b1010 J
b110010001000101 9
b110010001000101 G
b100 I
0'
b10000 .
b1101101101 H
0+
1&
#160000
0&
#165000
b100 F
b101 ?
b1 >
b1010 J
b101010101010100 9
b101010101010100 G
b100 I
b1011011010 H
1'
b10001 .
1+
1&
#170000
0&
#175000
b100 F
b101 ?
b1 >
b1010 J
b11010101010100 9
b11010101010100 G
b100 I
0'
b10010 .
b110110101 H
0+
1&
#180000
0&
#185000
b100 F
b110 ?
b0 >
b1010 J
b101001101010110 9
b101001101010110 G
b100 I
b1 )
b1101101010 H
1'
b10011 .
1+
1&
#190000
0&
#195000
0:
b10 >
b100 F
b111 ?
b1010 J
b111011101010100 9
b111011101010100 G
b100 I
b11000110 *
0'
b0 .
b1 ,
b1011010101 H
1&
#200000
0&
#205000
b100 F
1:
b110 ?
b1 >
b1010 J
b10010001100101 9
b10010001100101 G
b100 I
b110101010 H
b110001100 *
b1 .
0+
1&
#210000
0&
#215000
b100 F
b110 ?
b11 >
b1010 J
b110010000100011 9
b110010000100011 G
b100 I
b1100011000 *
b10 .
b1101010100 H
1+
1&
#220000
0&
#225000
b100 F
b101 ?
b1 >
b1010 J
b11001101010100 9
b11001101010100 G
b100 I
b1010101000 H
b1000110001 *
1'
b11 .
0+
1&
#230000
0&
#235000
b100 F
b110 ?
b0 >
b1010 J
b101010101010110 9
b101010101010110 G
b100 I
b1100011 *
b100 .
b101010001 H
1&
#240000
0&
#245000
b1 >
0:
b100 F
b1000 ?
b1010 J
b110011010000111 9
b110011010000111 G
b100 I
b1010100011 H
b11000110 *
0'
b101 .
1&
#250000
0&
#255000
b100 F
0:
b111 ?
b10 >
b1010 J
b111011101010110 9
b111011101010110 G
b100 I
b110001100 *
b110 .
b101000110 H
1+
1&
#260000
0&
#265000
b100 F
1:
b101 ?
b10 >
b1010 J
b101010100110010 9
b101010100110010 G
b100 I
b1010001100 H
b1100011000 *
b111 .
0+
1&
#270000
0&
#275000
b100 F
b11 ?
b0 >
b1010 J
b10001000100011 9
b10001000100011 G
b100 I
b1000110001 *
1'
b1000 .
b100011000 H
1+
1&
#280000
0&
#285000
b100 F
b110 ?
b1010 J
b101001101010110 9
b101001101010110 G
b100 I
b10 )
b1000110001 H
b1100011 *
b1001 .
1&
#290000
0&
#295000
1W
13
00
b1 C
1<
0:
b100 F
b1010 ?
b1010 J
b111011110011010 9
b111011110011010 G
b100 I
b0 .
b10 ,
b1100011 H
1&
#300000
0&
#305000
b10 >
b100 F
1<
0:
b1010 ?
b1010 J
b1000101010000111 9
b1000101010000111 G
b100 I
b1 B
b11000111 H
b1 Q
b1 V
b0 %
b0 1
b0 @
b1010 A
b1 E
b1 .
1&
#310000
0&
#315000
b100 F
0<
0:
b111 ?
b10 >
b10 B
07
05
b1010 J
b101011101010100 9
b101011101010100 G
b100 I
0'
b10 .
b1 =
b1 R
b10 Q
b10 V
1$
b110001111 H
0+
1&
#320000
0&
#325000
1!
1/
b10 C
b100 F
1:
b101 ?
b11 >
b1010 J
b101001100010010 9
b101001100010010 G
b100 I
b11 B
b1100011110 H
b10 R
b11 Q
b11 V
b10 =
b11 .
1&
#330000
0&
#335000
b100 F
b100 ?
b11 >
b0 B
0!
12
0/
b1010 J
b100001000100011 9
b100001000100011 G
b100 I
b100 .
b11 =
b10 E
b11 R
b100 Q
b100 V
b1000111100 H
1&
#340000
0&
#345000
b100 F
b110 ?
b0 >
b1010 J
b11001101010110 9
b11001101010110 G
b100 I
b1 M
b1111000 H
b100 R
b101 Q
b101 V
b1 N
b1 U
b0 A
1#
b0 =
b101 .
1&
#350000
0&
#355000
0:
b1 >
b100 F
b111 ?
b10 M
b1010 J
b11010101110110 9
b11010101110110 G
b100 I
b1 -
1'
b110 .
b101 R
b110 Q
b110 V
b10 N
b10 U
b11110000 H
1+
1&
#360000
0&
#365000
b100 F
0:
b1000 ?
b1 >
b1010 J
b100011010000111 9
b100011010000111 G
b100 I
b11 M
b111100001 H
0$
b110 R
b111 Q
b111 V
b11 N
b11 U
0'
b111 .
b10 -
0+
1&
#370000
0&
#375000
b100 F
1:
b110 ?
b1 >
b100 M
b1010 J
b110011001100101 9
b110011001100101 G
b100 I
b11 -
1'
b1000 .
b111 R
b1000 Q
b1000 V
b100 N
b100 U
b1111000010 H
1+
1&
#380000
0&
#385000
b100 F
b110 ?
b10 >
b1010 J
b110011001000011 9
b110011001000011 G
b100 I
b101 M
b1110000101 H
b1000 R
b1001 Q
b1001 V
b101 N
b101 U
b1001 .
b100 -
1&
#390000
0&
#395000
b100 F
b110 ?
b11 >
b110 M
b1010 J
b110010001000101 9
b110010001000101 G
b100 I
b101 -
b1010 .
b1001 R
b1010 Q
b1010 V
b110 N
b110 U
b1100001011 H
1&
#400000
0&
#405000
0:
b100 F
b1000 ?
b11 >
b1010 J
b1000011001000101 9
b1000011001000101 G
b100 I
b111 M
b1000010111 H
1$
b1010 R
b1011 Q
b1011 V
b111 N
b111 U
b1011 .
b110 -
1&
#410000
0&
#415000
b100 F
0:
b111 ?
b0 >
b1000 M
b1010 J
b110011001100111 9
b110011001100111 G
b100 I
b111 -
b1100 .
b1011 R
b1100 Q
b1100 V
b1000 N
b1000 U
0$
b101111 H
1&
#420000
0&
#425000
b10 >
b100 F
0:
b111 ?
b1010 J
b111011101010110 9
b111011101010110 G
b100 I
b1001 M
b1011111 H
1$
b1100 R
b1101 Q
b1101 V
b1001 N
b1001 U
0'
b1101 .
b1000 -
0+
1&
#430000
0&
#435000
b100 F
1:
b101 ?
b1 >
b1010 M
b1010 J
b11010101010100 9
b11010101010100 G
b100 I
b1001 -
b1110 .
b1101 R
b1110 Q
b1110 V
b1010 N
b1010 U
b10111110 H
1&
#440000
0&
#445000
b100 F
b100 ?
b0 >
b1010 J
b11001100110100 9
b11001100110100 G
b100 I
b1011 M
b101111100 H
b1110 R
b1111 Q
b1111 V
b1011 N
b1011 U
1'
b1111 .
b1010 -
1+
1&
#450000
0&
#455000
b1 >
b100 F
b110 ?
b1100 M
b1010 J
b100010001100101 9
b100010001100101 G
b100 I
b1011 -
b10000 .
b1111 R
b10000 Q
b10000 V
b1100 N
b1100 U
b1011111001 H
1&
#460000
0&
#465000
0:
b100 F
b1000 ?
b1 >
b1010 J
b100011010000111 9
b100011010000111 G
b100 I
b1101 M
b111110011 H
b10000 R
b10001 Q
b10001 V
b1101 N
b1101 U
b10001 .
b1100 -
1&
#470000
0&
#475000
b100 F
0:
b111 ?
b1 >
b1110 M
b1010 J
b111011101110110 9
b111011101110110 G
b100 I
b1101 -
0'
b10010 .
b10001 R
b10010 Q
b10010 V
b1110 N
b1110 U
0$
b1111100111 H
0+
1&
#480000
0&
#485000
b100 F
1:
b110 ?
b10 >
b1010 J
b110011001000011 9
b110011001000011 G
b100 I
b1111 M
b11 )
b1111001110 H
b10010 R
b10011 Q
b10011 V
b1111 N
b1111 U
b10011 .
b1110 -
1&
#490000
0&
#495000
b100 F
b11 ?
b10 >
b10000 M
b1010 J
b11001100010000 9
b11001100010000 G
b100 I
b1111 -
b0 .
b11 ,
b10011 R
b10100 Q
b10100 V
b10000 N
b10000 U
1$
b1110011100 H
1&
#500000
0&
#505000
b100 F
b11 ?
b0 >
b10000000100011 9
b10000000100011 G
b1010 J
b100 I
b10001 M
b1100111000 H
b10100 R
b10101 Q
b10101 V
b10001 N
b10001 U
b1 .
b10000 -
1&
#510000
0&
#515000
b100 F
b110 ?
b10010 M
b1010 J
b101001101010110 9
b101001101010110 G
b100 I
b10001 -
b10 .
b10101 R
b10110 Q
b10110 V
b10010 N
b10010 U
b1001110000 H
1&
#520000
0&
#525000
b1 >
0:
b100 F
b1000 ?
b1010 J
b100011010000111 9
b100011010000111 G
b100 I
b10011 M
b11100000 H
0$
b10110 R
b10111 Q
b10111 V
b10011 N
b10011 U
b11 .
b10010 -
1+
1&
#530000
0&
#535000
1"
b100 F
1:
b110 ?
b1 >
b0 C
b10100 M
b1010 J
b100011001100101 9
b100011001100101 G
b100 I
1;
b10011 -
b100 .
b10111 R
b11000 Q
b11000 V
b10100 N
b10100 U
b111000000 H
0+
1&
#540000
0&
#545000
0W
03
b100 F
b100 ?
b1 >
b1010 J
b100010001000011 9
b100010001000011 G
b100 I
b10101 M
0"
02
10
b1110000000 H
b11000 R
b11001 Q
b11001 V
b10101 N
b10101 U
b0 E
b101 .
b10100 -
1&
#550000
0&
#555000
b100 F
b101 ?
b11 >
17
15
b0 M
b1010 J
b101001100110100 9
b101001100110100 G
b100 I
b110 .
0#
b0 R
b0 Q
b0 V
b0 N
b0 U
b1100000000 H
1+
1&
#560000
0&
#565000
b100 F
b110 ?
b11 >
b1010 J
b110010001000101 9
b110010001000101 G
b100 I
b1000000000 H
1$
b111 .
1&
#570000
0&
#575000
b100 F
b110 ?
b0 >
b1010 J
b101010101010110 9
b101010101010110 G
b100 I
b1000 .
b0 H
0+
1&
#580000
0&
#585000
b1001 .
1&
#590000
0&
#595000
b1010 .
1&
#600000
0&
#605000
b1011 .
1&
#610000
0&
#615000
b1100 .
1&
#620000
0&
#625000
b1101 .
1+
1&
#630000
0&
#635000
b1110 .
1&
#640000
0&
#645000
b1111 .
1&
#650000
0&
#655000
b10000 .
1&
#660000
0&
#665000
b10001 .
1&
#670000
0&
#675000
b10010 .
0+
1&
#680000
0&
#685000
b0 )
b10011 .
1&
#690000
0&
#695000
1'
b0 .
b0 ,
1+
1&
#700000
0&
#705000
0:
b100 F
b111 ?
b1010 J
b110011001100111 9
b110011001100111 G
b100 I
0;
b1 H
b1 .
b0 -
1&
#710000
0&
#715000
b100 F
0:
b1000 ?
b1010 J
b111011101111000 9
b111011101111000 G
b100 I
b10 .
b11 H
1&
#720000
0&
#725000
b10 >
b100 F
0:
b1000 ?
b1010 J
b1000100001100111 9
b1000100001100111 G
b100 I
b111 H
0'
b11 .
0+
1&
#730000
0&
#735000
b100 F
1:
b110 ?
b10 >
b1010 J
b110011001000101 9
b110011001000101 G
b100 I
b100 .
b1110 H
1&
#740000
0&
#745000
b100 F
b100 ?
b10 >
b1010 J
b100010000100011 9
b100010000100011 G
b100 I
b11100 H
1'
b101 .
1+
1&
#750000
0&
#755000
b100 F
b110 ?
b0 >
b1010 J
b11001101010110 9
b11001101010110 G
b100 I
b110 .
b111001 H
1&
#760000
0&
#765000
0:
b100 F
b1001 ?
b1010 J
b110011010001001 9
b110011010001001 G
b100 I
b1110011 H
0'
b111 .
0+
1&
#770000
0&
#775000
b1 >
b100 F
0:
b1000 ?
b1010 J
b110100010000111 9
b110100010000111 G
b100 I
1'
b1000 .
b11100110 H
1+
1&
#780000
0&
#785000
b100 F
0:
b111 ?
b10 >
b1010 J
b101011101010100 9
b101011101010100 G
b100 I
b111001101 H
b1001 .
1&
#790000
0&
#795000
b100 F
1:
b100 ?
b1 >
b1010 J
b100010001000011 9
b100010001000011 G
b100 I
0'
b1010 .
b1110011011 H
0+
1&
#800000
0&
#805000
b100 F
b101 ?
b11 >
b1010 J
b101001100110100 9
b101001100110100 G
b100 I
b1100110110 H
1'
b1011 .
1+
1&
#810000
0&
#815000
0:
b100 F
b111 ?
b11 >
b1010 J
b111010101010110 9
b111010101010110 G
b100 I
b1100 .
b1001101101 H
1&
#820000
0&
#825000
b100 F
0:
b111 ?
b1 >
b1010 J
b101011101110110 9
b101011101110110 G
b100 I
b11011011 H
b1101 .
1&
#830000
0&
#835000
b100 F
1:
b110 ?
b1 >
b1010 J
b100011001100101 9
b100011001100101 G
b100 I
0'
b1110 .
b110110111 H
0+
1&
#840000
0&
#845000
b100 F
b110 ?
b11 >
b1010 J
b110010001000101 9
b110010001000101 G
b100 I
b1101101110 H
1'
b1111 .
1+
1&
#850000
0&
#855000
b100 F
b110 ?
b10 >
b1010 J
b110011001000011 9
b110011001000011 G
b100 I
b10000 .
b1011011101 H
1&
#860000
0&
